{
    "demandLength": 30,
    "supplyLength": 30,
    "costMatrix": [
        {
            "val": 7.92,
            "s": 1,
            "d": 1
        },
        {
            "val": 19.841,
            "s": 2,
            "d": 1
        },
        {
            "val": 17.137,
            "s": 3,
            "d": 1
        },
        {
            "val": 12.857,
            "s": 4,
            "d": 1
        },
        {
            "val": 15.031,
            "s": 5,
            "d": 1
        },
        {
            "val": 11.295,
            "s": 6,
            "d": 1
        },
        {
            "val": 6.112,
            "s": 7,
            "d": 1
        },
        {
            "val": 16.964,
            "s": 8,
            "d": 1
        },
        {
            "val": 18.956,
            "s": 9,
            "d": 1
        },
        {
            "val": 11.07,
            "s": 10,
            "d": 1
        },
        {
            "val": 19.376,
            "s": 11,
            "d": 1
        },
        {
            "val": 7.596,
            "s": 12,
            "d": 1
        },
        {
            "val": 12.703,
            "s": 13,
            "d": 1
        },
        {
            "val": 9.872,
            "s": 14,
            "d": 1
        },
        {
            "val": 7.957,
            "s": 15,
            "d": 1
        },
        {
            "val": 15.756,
            "s": 16,
            "d": 1
        },
        {
            "val": 17.87,
            "s": 17,
            "d": 1
        },
        {
            "val": 15.647,
            "s": 18,
            "d": 1
        },
        {
            "val": 7.015,
            "s": 19,
            "d": 1
        },
        {
            "val": 8.03,
            "s": 20,
            "d": 1
        },
        {
            "val": 19.845,
            "s": 21,
            "d": 1
        },
        {
            "val": 7.602,
            "s": 22,
            "d": 1
        },
        {
            "val": 5.703,
            "s": 23,
            "d": 1
        },
        {
            "val": 18.402,
            "s": 24,
            "d": 1
        },
        {
            "val": 12.568,
            "s": 25,
            "d": 1
        },
        {
            "val": 5.079,
            "s": 26,
            "d": 1
        },
        {
            "val": 17.701,
            "s": 27,
            "d": 1
        },
        {
            "val": 18.766,
            "s": 28,
            "d": 1
        },
        {
            "val": 14.224,
            "s": 29,
            "d": 1
        },
        {
            "val": 8.146,
            "s": 30,
            "d": 1
        },
        {
            "val": 6.321,
            "s": 1,
            "d": 2
        },
        {
            "val": 10.338,
            "s": 2,
            "d": 2
        },
        {
            "val": 18.655,
            "s": 3,
            "d": 2
        },
        {
            "val": 11.841,
            "s": 4,
            "d": 2
        },
        {
            "val": 8.501,
            "s": 5,
            "d": 2
        },
        {
            "val": 10.803,
            "s": 6,
            "d": 2
        },
        {
            "val": 9.793,
            "s": 7,
            "d": 2
        },
        {
            "val": 10.059,
            "s": 8,
            "d": 2
        },
        {
            "val": 13.176,
            "s": 9,
            "d": 2
        },
        {
            "val": 11.674,
            "s": 10,
            "d": 2
        },
        {
            "val": 13.48,
            "s": 11,
            "d": 2
        },
        {
            "val": 5.882,
            "s": 12,
            "d": 2
        },
        {
            "val": 6.184,
            "s": 13,
            "d": 2
        },
        {
            "val": 13.796,
            "s": 14,
            "d": 2
        },
        {
            "val": 7.011,
            "s": 15,
            "d": 2
        },
        {
            "val": 5.021,
            "s": 16,
            "d": 2
        },
        {
            "val": 17.679,
            "s": 17,
            "d": 2
        },
        {
            "val": 7.412,
            "s": 18,
            "d": 2
        },
        {
            "val": 8.464,
            "s": 19,
            "d": 2
        },
        {
            "val": 7.854,
            "s": 20,
            "d": 2
        },
        {
            "val": 14.68,
            "s": 21,
            "d": 2
        },
        {
            "val": 15.438,
            "s": 22,
            "d": 2
        },
        {
            "val": 6.106,
            "s": 23,
            "d": 2
        },
        {
            "val": 9.59,
            "s": 24,
            "d": 2
        },
        {
            "val": 8.38,
            "s": 25,
            "d": 2
        },
        {
            "val": 13.129,
            "s": 26,
            "d": 2
        },
        {
            "val": 8.999,
            "s": 27,
            "d": 2
        },
        {
            "val": 11.686,
            "s": 28,
            "d": 2
        },
        {
            "val": 9.031,
            "s": 29,
            "d": 2
        },
        {
            "val": 8.63,
            "s": 30,
            "d": 2
        },
        {
            "val": 12.715,
            "s": 1,
            "d": 3
        },
        {
            "val": 18.182,
            "s": 2,
            "d": 3
        },
        {
            "val": 11.557,
            "s": 3,
            "d": 3
        },
        {
            "val": 8.473,
            "s": 4,
            "d": 3
        },
        {
            "val": 8.419,
            "s": 5,
            "d": 3
        },
        {
            "val": 5.254,
            "s": 6,
            "d": 3
        },
        {
            "val": 17.079,
            "s": 7,
            "d": 3
        },
        {
            "val": 15.126,
            "s": 8,
            "d": 3
        },
        {
            "val": 13.515,
            "s": 9,
            "d": 3
        },
        {
            "val": 19.876,
            "s": 10,
            "d": 3
        },
        {
            "val": 10.055,
            "s": 11,
            "d": 3
        },
        {
            "val": 18.508,
            "s": 12,
            "d": 3
        },
        {
            "val": 15.615,
            "s": 13,
            "d": 3
        },
        {
            "val": 11.335,
            "s": 14,
            "d": 3
        },
        {
            "val": 19.455,
            "s": 15,
            "d": 3
        },
        {
            "val": 13.948,
            "s": 16,
            "d": 3
        },
        {
            "val": 7.255,
            "s": 17,
            "d": 3
        },
        {
            "val": 19.22,
            "s": 18,
            "d": 3
        },
        {
            "val": 5.77,
            "s": 19,
            "d": 3
        },
        {
            "val": 6.064,
            "s": 20,
            "d": 3
        },
        {
            "val": 12.327,
            "s": 21,
            "d": 3
        },
        {
            "val": 9.075,
            "s": 22,
            "d": 3
        },
        {
            "val": 7.578,
            "s": 23,
            "d": 3
        },
        {
            "val": 9.296,
            "s": 24,
            "d": 3
        },
        {
            "val": 5.801,
            "s": 25,
            "d": 3
        },
        {
            "val": 5.507,
            "s": 26,
            "d": 3
        },
        {
            "val": 16.951,
            "s": 27,
            "d": 3
        },
        {
            "val": 6.28,
            "s": 28,
            "d": 3
        },
        {
            "val": 15.895,
            "s": 29,
            "d": 3
        },
        {
            "val": 19.299,
            "s": 30,
            "d": 3
        },
        {
            "val": 8.711,
            "s": 1,
            "d": 4
        },
        {
            "val": 6.822,
            "s": 2,
            "d": 4
        },
        {
            "val": 18.122,
            "s": 3,
            "d": 4
        },
        {
            "val": 19.912,
            "s": 4,
            "d": 4
        },
        {
            "val": 19.864,
            "s": 5,
            "d": 4
        },
        {
            "val": 15.488,
            "s": 6,
            "d": 4
        },
        {
            "val": 7.144,
            "s": 7,
            "d": 4
        },
        {
            "val": 18.702,
            "s": 8,
            "d": 4
        },
        {
            "val": 10.631,
            "s": 9,
            "d": 4
        },
        {
            "val": 18.827,
            "s": 10,
            "d": 4
        },
        {
            "val": 19.105,
            "s": 11,
            "d": 4
        },
        {
            "val": 13.463,
            "s": 12,
            "d": 4
        },
        {
            "val": 13.007,
            "s": 13,
            "d": 4
        },
        {
            "val": 6.993,
            "s": 14,
            "d": 4
        },
        {
            "val": 15.353,
            "s": 15,
            "d": 4
        },
        {
            "val": 9.754,
            "s": 16,
            "d": 4
        },
        {
            "val": 16.697,
            "s": 17,
            "d": 4
        },
        {
            "val": 9.63,
            "s": 18,
            "d": 4
        },
        {
            "val": 5.783,
            "s": 19,
            "d": 4
        },
        {
            "val": 19.318,
            "s": 20,
            "d": 4
        },
        {
            "val": 9.255,
            "s": 21,
            "d": 4
        },
        {
            "val": 18.987,
            "s": 22,
            "d": 4
        },
        {
            "val": 13.213,
            "s": 23,
            "d": 4
        },
        {
            "val": 12.065,
            "s": 24,
            "d": 4
        },
        {
            "val": 16.077,
            "s": 25,
            "d": 4
        },
        {
            "val": 16.762,
            "s": 26,
            "d": 4
        },
        {
            "val": 6.803,
            "s": 27,
            "d": 4
        },
        {
            "val": 13.485,
            "s": 28,
            "d": 4
        },
        {
            "val": 12.574,
            "s": 29,
            "d": 4
        },
        {
            "val": 17.787,
            "s": 30,
            "d": 4
        },
        {
            "val": 6.103,
            "s": 1,
            "d": 5
        },
        {
            "val": 15.537,
            "s": 2,
            "d": 5
        },
        {
            "val": 16.203,
            "s": 3,
            "d": 5
        },
        {
            "val": 17.627,
            "s": 4,
            "d": 5
        },
        {
            "val": 11.659,
            "s": 5,
            "d": 5
        },
        {
            "val": 10.332,
            "s": 6,
            "d": 5
        },
        {
            "val": 9.805,
            "s": 7,
            "d": 5
        },
        {
            "val": 6.646,
            "s": 8,
            "d": 5
        },
        {
            "val": 15.231,
            "s": 9,
            "d": 5
        },
        {
            "val": 17.745,
            "s": 10,
            "d": 5
        },
        {
            "val": 7.191,
            "s": 11,
            "d": 5
        },
        {
            "val": 15.369,
            "s": 12,
            "d": 5
        },
        {
            "val": 19.437,
            "s": 13,
            "d": 5
        },
        {
            "val": 7.649,
            "s": 14,
            "d": 5
        },
        {
            "val": 14.68,
            "s": 15,
            "d": 5
        },
        {
            "val": 19.64,
            "s": 16,
            "d": 5
        },
        {
            "val": 7.684,
            "s": 17,
            "d": 5
        },
        {
            "val": 18.735,
            "s": 18,
            "d": 5
        },
        {
            "val": 10.788,
            "s": 19,
            "d": 5
        },
        {
            "val": 12.777,
            "s": 20,
            "d": 5
        },
        {
            "val": 13.522,
            "s": 21,
            "d": 5
        },
        {
            "val": 8.705,
            "s": 22,
            "d": 5
        },
        {
            "val": 17.43,
            "s": 23,
            "d": 5
        },
        {
            "val": 16.826,
            "s": 24,
            "d": 5
        },
        {
            "val": 5.05,
            "s": 25,
            "d": 5
        },
        {
            "val": 5.946,
            "s": 26,
            "d": 5
        },
        {
            "val": 6.859,
            "s": 27,
            "d": 5
        },
        {
            "val": 14.017,
            "s": 28,
            "d": 5
        },
        {
            "val": 5.938,
            "s": 29,
            "d": 5
        },
        {
            "val": 9.041,
            "s": 30,
            "d": 5
        },
        {
            "val": 5.514,
            "s": 1,
            "d": 6
        },
        {
            "val": 17.781,
            "s": 2,
            "d": 6
        },
        {
            "val": 19.555,
            "s": 3,
            "d": 6
        },
        {
            "val": 17.804,
            "s": 4,
            "d": 6
        },
        {
            "val": 17.718,
            "s": 5,
            "d": 6
        },
        {
            "val": 9.213,
            "s": 6,
            "d": 6
        },
        {
            "val": 8.7,
            "s": 7,
            "d": 6
        },
        {
            "val": 14.786,
            "s": 8,
            "d": 6
        },
        {
            "val": 17.9,
            "s": 9,
            "d": 6
        },
        {
            "val": 6.581,
            "s": 10,
            "d": 6
        },
        {
            "val": 17.357,
            "s": 11,
            "d": 6
        },
        {
            "val": 10.418,
            "s": 12,
            "d": 6
        },
        {
            "val": 6.952,
            "s": 13,
            "d": 6
        },
        {
            "val": 5.711,
            "s": 14,
            "d": 6
        },
        {
            "val": 7.316,
            "s": 15,
            "d": 6
        },
        {
            "val": 10.908,
            "s": 16,
            "d": 6
        },
        {
            "val": 19.633,
            "s": 17,
            "d": 6
        },
        {
            "val": 16.366,
            "s": 18,
            "d": 6
        },
        {
            "val": 14.292,
            "s": 19,
            "d": 6
        },
        {
            "val": 13.228,
            "s": 20,
            "d": 6
        },
        {
            "val": 8.384,
            "s": 21,
            "d": 6
        },
        {
            "val": 13.643,
            "s": 22,
            "d": 6
        },
        {
            "val": 17.507,
            "s": 23,
            "d": 6
        },
        {
            "val": 15.234,
            "s": 24,
            "d": 6
        },
        {
            "val": 16.746,
            "s": 25,
            "d": 6
        },
        {
            "val": 7.351,
            "s": 26,
            "d": 6
        },
        {
            "val": 13.546,
            "s": 27,
            "d": 6
        },
        {
            "val": 12.663,
            "s": 28,
            "d": 6
        },
        {
            "val": 13.718,
            "s": 29,
            "d": 6
        },
        {
            "val": 15.106,
            "s": 30,
            "d": 6
        },
        {
            "val": 19.376,
            "s": 1,
            "d": 7
        },
        {
            "val": 12.337,
            "s": 2,
            "d": 7
        },
        {
            "val": 8.124,
            "s": 3,
            "d": 7
        },
        {
            "val": 6.077,
            "s": 4,
            "d": 7
        },
        {
            "val": 15.561,
            "s": 5,
            "d": 7
        },
        {
            "val": 19.312,
            "s": 6,
            "d": 7
        },
        {
            "val": 15.838,
            "s": 7,
            "d": 7
        },
        {
            "val": 11.55,
            "s": 8,
            "d": 7
        },
        {
            "val": 10.854,
            "s": 9,
            "d": 7
        },
        {
            "val": 11.464,
            "s": 10,
            "d": 7
        },
        {
            "val": 10.949,
            "s": 11,
            "d": 7
        },
        {
            "val": 5.762,
            "s": 12,
            "d": 7
        },
        {
            "val": 18.889,
            "s": 13,
            "d": 7
        },
        {
            "val": 13.238,
            "s": 14,
            "d": 7
        },
        {
            "val": 7.918,
            "s": 15,
            "d": 7
        },
        {
            "val": 15.911,
            "s": 16,
            "d": 7
        },
        {
            "val": 7.152,
            "s": 17,
            "d": 7
        },
        {
            "val": 15.436,
            "s": 18,
            "d": 7
        },
        {
            "val": 5.668,
            "s": 19,
            "d": 7
        },
        {
            "val": 17.861,
            "s": 20,
            "d": 7
        },
        {
            "val": 5.153,
            "s": 21,
            "d": 7
        },
        {
            "val": 16.667,
            "s": 22,
            "d": 7
        },
        {
            "val": 6.442,
            "s": 23,
            "d": 7
        },
        {
            "val": 10.435,
            "s": 24,
            "d": 7
        },
        {
            "val": 7.471,
            "s": 25,
            "d": 7
        },
        {
            "val": 5.171,
            "s": 26,
            "d": 7
        },
        {
            "val": 12.32,
            "s": 27,
            "d": 7
        },
        {
            "val": 9.141,
            "s": 28,
            "d": 7
        },
        {
            "val": 17.39,
            "s": 29,
            "d": 7
        },
        {
            "val": 14.916,
            "s": 30,
            "d": 7
        },
        {
            "val": 7.635,
            "s": 1,
            "d": 8
        },
        {
            "val": 8.249,
            "s": 2,
            "d": 8
        },
        {
            "val": 10.076,
            "s": 3,
            "d": 8
        },
        {
            "val": 13.105,
            "s": 4,
            "d": 8
        },
        {
            "val": 12.048,
            "s": 5,
            "d": 8
        },
        {
            "val": 19.353,
            "s": 6,
            "d": 8
        },
        {
            "val": 8.648,
            "s": 7,
            "d": 8
        },
        {
            "val": 6.067,
            "s": 8,
            "d": 8
        },
        {
            "val": 15.023,
            "s": 9,
            "d": 8
        },
        {
            "val": 11.318,
            "s": 10,
            "d": 8
        },
        {
            "val": 5.963,
            "s": 11,
            "d": 8
        },
        {
            "val": 18.044,
            "s": 12,
            "d": 8
        },
        {
            "val": 7.65,
            "s": 13,
            "d": 8
        },
        {
            "val": 19.075,
            "s": 14,
            "d": 8
        },
        {
            "val": 9.393,
            "s": 15,
            "d": 8
        },
        {
            "val": 18.998,
            "s": 16,
            "d": 8
        },
        {
            "val": 16.187,
            "s": 17,
            "d": 8
        },
        {
            "val": 13.148,
            "s": 18,
            "d": 8
        },
        {
            "val": 9.866,
            "s": 19,
            "d": 8
        },
        {
            "val": 12.644,
            "s": 20,
            "d": 8
        },
        {
            "val": 11.895,
            "s": 21,
            "d": 8
        },
        {
            "val": 8.222,
            "s": 22,
            "d": 8
        },
        {
            "val": 10.091,
            "s": 23,
            "d": 8
        },
        {
            "val": 9.146,
            "s": 24,
            "d": 8
        },
        {
            "val": 15.52,
            "s": 25,
            "d": 8
        },
        {
            "val": 8.011,
            "s": 26,
            "d": 8
        },
        {
            "val": 19.496,
            "s": 27,
            "d": 8
        },
        {
            "val": 11.998,
            "s": 28,
            "d": 8
        },
        {
            "val": 10.756,
            "s": 29,
            "d": 8
        },
        {
            "val": 6.963,
            "s": 30,
            "d": 8
        },
        {
            "val": 7.213,
            "s": 1,
            "d": 9
        },
        {
            "val": 19.665,
            "s": 2,
            "d": 9
        },
        {
            "val": 8.324,
            "s": 3,
            "d": 9
        },
        {
            "val": 10.085,
            "s": 4,
            "d": 9
        },
        {
            "val": 6.392,
            "s": 5,
            "d": 9
        },
        {
            "val": 12.646,
            "s": 6,
            "d": 9
        },
        {
            "val": 15.41,
            "s": 7,
            "d": 9
        },
        {
            "val": 11.213,
            "s": 8,
            "d": 9
        },
        {
            "val": 10.771,
            "s": 9,
            "d": 9
        },
        {
            "val": 5.443,
            "s": 10,
            "d": 9
        },
        {
            "val": 5.251,
            "s": 11,
            "d": 9
        },
        {
            "val": 5.344,
            "s": 12,
            "d": 9
        },
        {
            "val": 19.703,
            "s": 13,
            "d": 9
        },
        {
            "val": 18.573,
            "s": 14,
            "d": 9
        },
        {
            "val": 6.631,
            "s": 15,
            "d": 9
        },
        {
            "val": 19.787,
            "s": 16,
            "d": 9
        },
        {
            "val": 8.685,
            "s": 17,
            "d": 9
        },
        {
            "val": 8.784,
            "s": 18,
            "d": 9
        },
        {
            "val": 8.952,
            "s": 19,
            "d": 9
        },
        {
            "val": 13.524,
            "s": 20,
            "d": 9
        },
        {
            "val": 7.782,
            "s": 21,
            "d": 9
        },
        {
            "val": 11.081,
            "s": 22,
            "d": 9
        },
        {
            "val": 10.3,
            "s": 23,
            "d": 9
        },
        {
            "val": 15.033,
            "s": 24,
            "d": 9
        },
        {
            "val": 13.903,
            "s": 25,
            "d": 9
        },
        {
            "val": 13.309,
            "s": 26,
            "d": 9
        },
        {
            "val": 19.147,
            "s": 27,
            "d": 9
        },
        {
            "val": 19.184,
            "s": 28,
            "d": 9
        },
        {
            "val": 10.195,
            "s": 29,
            "d": 9
        },
        {
            "val": 8.895,
            "s": 30,
            "d": 9
        },
        {
            "val": 13.915,
            "s": 1,
            "d": 10
        },
        {
            "val": 15.301,
            "s": 2,
            "d": 10
        },
        {
            "val": 14.911,
            "s": 3,
            "d": 10
        },
        {
            "val": 7.988,
            "s": 4,
            "d": 10
        },
        {
            "val": 19.582,
            "s": 5,
            "d": 10
        },
        {
            "val": 19.873,
            "s": 6,
            "d": 10
        },
        {
            "val": 14.203,
            "s": 7,
            "d": 10
        },
        {
            "val": 6.784,
            "s": 8,
            "d": 10
        },
        {
            "val": 10.731,
            "s": 9,
            "d": 10
        },
        {
            "val": 18.766,
            "s": 10,
            "d": 10
        },
        {
            "val": 14.584,
            "s": 11,
            "d": 10
        },
        {
            "val": 9.699,
            "s": 12,
            "d": 10
        },
        {
            "val": 9.261,
            "s": 13,
            "d": 10
        },
        {
            "val": 11.92,
            "s": 14,
            "d": 10
        },
        {
            "val": 6.961,
            "s": 15,
            "d": 10
        },
        {
            "val": 14.48,
            "s": 16,
            "d": 10
        },
        {
            "val": 14.958,
            "s": 17,
            "d": 10
        },
        {
            "val": 15.17,
            "s": 18,
            "d": 10
        },
        {
            "val": 13.017,
            "s": 19,
            "d": 10
        },
        {
            "val": 7.385,
            "s": 20,
            "d": 10
        },
        {
            "val": 8.588,
            "s": 21,
            "d": 10
        },
        {
            "val": 6.911,
            "s": 22,
            "d": 10
        },
        {
            "val": 19.995,
            "s": 23,
            "d": 10
        },
        {
            "val": 5.506,
            "s": 24,
            "d": 10
        },
        {
            "val": 11.764,
            "s": 25,
            "d": 10
        },
        {
            "val": 15.371,
            "s": 26,
            "d": 10
        },
        {
            "val": 15.754,
            "s": 27,
            "d": 10
        },
        {
            "val": 19.276,
            "s": 28,
            "d": 10
        },
        {
            "val": 7.791,
            "s": 29,
            "d": 10
        },
        {
            "val": 13.621,
            "s": 30,
            "d": 10
        },
        {
            "val": 8.094,
            "s": 1,
            "d": 11
        },
        {
            "val": 12.956,
            "s": 2,
            "d": 11
        },
        {
            "val": 11.743,
            "s": 3,
            "d": 11
        },
        {
            "val": 19.852,
            "s": 4,
            "d": 11
        },
        {
            "val": 12.82,
            "s": 5,
            "d": 11
        },
        {
            "val": 8.427,
            "s": 6,
            "d": 11
        },
        {
            "val": 18.86,
            "s": 7,
            "d": 11
        },
        {
            "val": 10.894,
            "s": 8,
            "d": 11
        },
        {
            "val": 10.748,
            "s": 9,
            "d": 11
        },
        {
            "val": 12.643,
            "s": 10,
            "d": 11
        },
        {
            "val": 5.62,
            "s": 11,
            "d": 11
        },
        {
            "val": 8.184,
            "s": 12,
            "d": 11
        },
        {
            "val": 14.085,
            "s": 13,
            "d": 11
        },
        {
            "val": 10.173,
            "s": 14,
            "d": 11
        },
        {
            "val": 9.406,
            "s": 15,
            "d": 11
        },
        {
            "val": 13.764,
            "s": 16,
            "d": 11
        },
        {
            "val": 7.834,
            "s": 17,
            "d": 11
        },
        {
            "val": 13.945,
            "s": 18,
            "d": 11
        },
        {
            "val": 19.874,
            "s": 19,
            "d": 11
        },
        {
            "val": 11.935,
            "s": 20,
            "d": 11
        },
        {
            "val": 17.9,
            "s": 21,
            "d": 11
        },
        {
            "val": 19.477,
            "s": 22,
            "d": 11
        },
        {
            "val": 16.083,
            "s": 23,
            "d": 11
        },
        {
            "val": 7.244,
            "s": 24,
            "d": 11
        },
        {
            "val": 13.28,
            "s": 25,
            "d": 11
        },
        {
            "val": 18.517,
            "s": 26,
            "d": 11
        },
        {
            "val": 12.624,
            "s": 27,
            "d": 11
        },
        {
            "val": 11.039,
            "s": 28,
            "d": 11
        },
        {
            "val": 9.137,
            "s": 29,
            "d": 11
        },
        {
            "val": 5.137,
            "s": 30,
            "d": 11
        },
        {
            "val": 8.747,
            "s": 1,
            "d": 12
        },
        {
            "val": 14.828,
            "s": 2,
            "d": 12
        },
        {
            "val": 16.955,
            "s": 3,
            "d": 12
        },
        {
            "val": 13.85,
            "s": 4,
            "d": 12
        },
        {
            "val": 14.125,
            "s": 5,
            "d": 12
        },
        {
            "val": 14.184,
            "s": 6,
            "d": 12
        },
        {
            "val": 17.432,
            "s": 7,
            "d": 12
        },
        {
            "val": 17.836,
            "s": 8,
            "d": 12
        },
        {
            "val": 12.616,
            "s": 9,
            "d": 12
        },
        {
            "val": 19.439,
            "s": 10,
            "d": 12
        },
        {
            "val": 10.709,
            "s": 11,
            "d": 12
        },
        {
            "val": 19.413,
            "s": 12,
            "d": 12
        },
        {
            "val": 14.069,
            "s": 13,
            "d": 12
        },
        {
            "val": 9.224,
            "s": 14,
            "d": 12
        },
        {
            "val": 17.709,
            "s": 15,
            "d": 12
        },
        {
            "val": 18.492,
            "s": 16,
            "d": 12
        },
        {
            "val": 10.237,
            "s": 17,
            "d": 12
        },
        {
            "val": 19.037,
            "s": 18,
            "d": 12
        },
        {
            "val": 16.484,
            "s": 19,
            "d": 12
        },
        {
            "val": 6.587,
            "s": 20,
            "d": 12
        },
        {
            "val": 5.746,
            "s": 21,
            "d": 12
        },
        {
            "val": 7.443,
            "s": 22,
            "d": 12
        },
        {
            "val": 9.246,
            "s": 23,
            "d": 12
        },
        {
            "val": 5.501,
            "s": 24,
            "d": 12
        },
        {
            "val": 9.233,
            "s": 25,
            "d": 12
        },
        {
            "val": 11.205,
            "s": 26,
            "d": 12
        },
        {
            "val": 19.547,
            "s": 27,
            "d": 12
        },
        {
            "val": 6.05,
            "s": 28,
            "d": 12
        },
        {
            "val": 18.53,
            "s": 29,
            "d": 12
        },
        {
            "val": 6.476,
            "s": 30,
            "d": 12
        },
        {
            "val": 15.751,
            "s": 1,
            "d": 13
        },
        {
            "val": 10.89,
            "s": 2,
            "d": 13
        },
        {
            "val": 8.661,
            "s": 3,
            "d": 13
        },
        {
            "val": 6.33,
            "s": 4,
            "d": 13
        },
        {
            "val": 18.026,
            "s": 5,
            "d": 13
        },
        {
            "val": 8.134,
            "s": 6,
            "d": 13
        },
        {
            "val": 17.184,
            "s": 7,
            "d": 13
        },
        {
            "val": 12.767,
            "s": 8,
            "d": 13
        },
        {
            "val": 9.806,
            "s": 9,
            "d": 13
        },
        {
            "val": 7.501,
            "s": 10,
            "d": 13
        },
        {
            "val": 11.983,
            "s": 11,
            "d": 13
        },
        {
            "val": 16.245,
            "s": 12,
            "d": 13
        },
        {
            "val": 14.931,
            "s": 13,
            "d": 13
        },
        {
            "val": 6.653,
            "s": 14,
            "d": 13
        },
        {
            "val": 12.595,
            "s": 15,
            "d": 13
        },
        {
            "val": 13.517,
            "s": 16,
            "d": 13
        },
        {
            "val": 10.916,
            "s": 17,
            "d": 13
        },
        {
            "val": 15.311,
            "s": 18,
            "d": 13
        },
        {
            "val": 13.973,
            "s": 19,
            "d": 13
        },
        {
            "val": 9.993,
            "s": 20,
            "d": 13
        },
        {
            "val": 18.265,
            "s": 21,
            "d": 13
        },
        {
            "val": 14.54,
            "s": 22,
            "d": 13
        },
        {
            "val": 9.048,
            "s": 23,
            "d": 13
        },
        {
            "val": 6.842,
            "s": 24,
            "d": 13
        },
        {
            "val": 7.841,
            "s": 25,
            "d": 13
        },
        {
            "val": 8.464,
            "s": 26,
            "d": 13
        },
        {
            "val": 18.126,
            "s": 27,
            "d": 13
        },
        {
            "val": 5.311,
            "s": 28,
            "d": 13
        },
        {
            "val": 18.044,
            "s": 29,
            "d": 13
        },
        {
            "val": 12.468,
            "s": 30,
            "d": 13
        },
        {
            "val": 9.588,
            "s": 1,
            "d": 14
        },
        {
            "val": 8.685,
            "s": 2,
            "d": 14
        },
        {
            "val": 7.926,
            "s": 3,
            "d": 14
        },
        {
            "val": 16.71,
            "s": 4,
            "d": 14
        },
        {
            "val": 16.923,
            "s": 5,
            "d": 14
        },
        {
            "val": 7.683,
            "s": 6,
            "d": 14
        },
        {
            "val": 16.401,
            "s": 7,
            "d": 14
        },
        {
            "val": 19.27,
            "s": 8,
            "d": 14
        },
        {
            "val": 8.027,
            "s": 9,
            "d": 14
        },
        {
            "val": 19.586,
            "s": 10,
            "d": 14
        },
        {
            "val": 5.869,
            "s": 11,
            "d": 14
        },
        {
            "val": 14.06,
            "s": 12,
            "d": 14
        },
        {
            "val": 10.87,
            "s": 13,
            "d": 14
        },
        {
            "val": 9.104,
            "s": 14,
            "d": 14
        },
        {
            "val": 7.723,
            "s": 15,
            "d": 14
        },
        {
            "val": 17.978,
            "s": 16,
            "d": 14
        },
        {
            "val": 11.153,
            "s": 17,
            "d": 14
        },
        {
            "val": 14.917,
            "s": 18,
            "d": 14
        },
        {
            "val": 14.68,
            "s": 19,
            "d": 14
        },
        {
            "val": 11.93,
            "s": 20,
            "d": 14
        },
        {
            "val": 15.081,
            "s": 21,
            "d": 14
        },
        {
            "val": 18.595,
            "s": 22,
            "d": 14
        },
        {
            "val": 5.128,
            "s": 23,
            "d": 14
        },
        {
            "val": 12.837,
            "s": 24,
            "d": 14
        },
        {
            "val": 6.588,
            "s": 25,
            "d": 14
        },
        {
            "val": 18.096,
            "s": 26,
            "d": 14
        },
        {
            "val": 6.06,
            "s": 27,
            "d": 14
        },
        {
            "val": 6.423,
            "s": 28,
            "d": 14
        },
        {
            "val": 11.875,
            "s": 29,
            "d": 14
        },
        {
            "val": 16.864,
            "s": 30,
            "d": 14
        },
        {
            "val": 9.351,
            "s": 1,
            "d": 15
        },
        {
            "val": 7.898,
            "s": 2,
            "d": 15
        },
        {
            "val": 8.219,
            "s": 3,
            "d": 15
        },
        {
            "val": 6.117,
            "s": 4,
            "d": 15
        },
        {
            "val": 17.465,
            "s": 5,
            "d": 15
        },
        {
            "val": 5.629,
            "s": 6,
            "d": 15
        },
        {
            "val": 7.577,
            "s": 7,
            "d": 15
        },
        {
            "val": 5.507,
            "s": 8,
            "d": 15
        },
        {
            "val": 5.923,
            "s": 9,
            "d": 15
        },
        {
            "val": 19.367,
            "s": 10,
            "d": 15
        },
        {
            "val": 13.11,
            "s": 11,
            "d": 15
        },
        {
            "val": 10.637,
            "s": 12,
            "d": 15
        },
        {
            "val": 19.399,
            "s": 13,
            "d": 15
        },
        {
            "val": 13.581,
            "s": 14,
            "d": 15
        },
        {
            "val": 11.32,
            "s": 15,
            "d": 15
        },
        {
            "val": 7.307,
            "s": 16,
            "d": 15
        },
        {
            "val": 10.105,
            "s": 17,
            "d": 15
        },
        {
            "val": 16.921,
            "s": 18,
            "d": 15
        },
        {
            "val": 12.485,
            "s": 19,
            "d": 15
        },
        {
            "val": 8.41,
            "s": 20,
            "d": 15
        },
        {
            "val": 19.735,
            "s": 21,
            "d": 15
        },
        {
            "val": 16.177,
            "s": 22,
            "d": 15
        },
        {
            "val": 14.02,
            "s": 23,
            "d": 15
        },
        {
            "val": 13.98,
            "s": 24,
            "d": 15
        },
        {
            "val": 14.023,
            "s": 25,
            "d": 15
        },
        {
            "val": 14.977,
            "s": 26,
            "d": 15
        },
        {
            "val": 13.589,
            "s": 27,
            "d": 15
        },
        {
            "val": 19.034,
            "s": 28,
            "d": 15
        },
        {
            "val": 13.928,
            "s": 29,
            "d": 15
        },
        {
            "val": 7.613,
            "s": 30,
            "d": 15
        },
        {
            "val": 8.113,
            "s": 1,
            "d": 16
        },
        {
            "val": 9.21,
            "s": 2,
            "d": 16
        },
        {
            "val": 12.918,
            "s": 3,
            "d": 16
        },
        {
            "val": 11.01,
            "s": 4,
            "d": 16
        },
        {
            "val": 6.802,
            "s": 5,
            "d": 16
        },
        {
            "val": 7.855,
            "s": 6,
            "d": 16
        },
        {
            "val": 14.43,
            "s": 7,
            "d": 16
        },
        {
            "val": 15.97,
            "s": 8,
            "d": 16
        },
        {
            "val": 14.56,
            "s": 9,
            "d": 16
        },
        {
            "val": 14.134,
            "s": 10,
            "d": 16
        },
        {
            "val": 12.282,
            "s": 11,
            "d": 16
        },
        {
            "val": 6.186,
            "s": 12,
            "d": 16
        },
        {
            "val": 16.156,
            "s": 13,
            "d": 16
        },
        {
            "val": 11.355,
            "s": 14,
            "d": 16
        },
        {
            "val": 16.787,
            "s": 15,
            "d": 16
        },
        {
            "val": 16.04,
            "s": 16,
            "d": 16
        },
        {
            "val": 12.776,
            "s": 17,
            "d": 16
        },
        {
            "val": 19.03,
            "s": 18,
            "d": 16
        },
        {
            "val": 15.936,
            "s": 19,
            "d": 16
        },
        {
            "val": 14.703,
            "s": 20,
            "d": 16
        },
        {
            "val": 7.505,
            "s": 21,
            "d": 16
        },
        {
            "val": 12.071,
            "s": 22,
            "d": 16
        },
        {
            "val": 13.031,
            "s": 23,
            "d": 16
        },
        {
            "val": 5.178,
            "s": 24,
            "d": 16
        },
        {
            "val": 8.949,
            "s": 25,
            "d": 16
        },
        {
            "val": 14.735,
            "s": 26,
            "d": 16
        },
        {
            "val": 7.505,
            "s": 27,
            "d": 16
        },
        {
            "val": 7.721,
            "s": 28,
            "d": 16
        },
        {
            "val": 11.295,
            "s": 29,
            "d": 16
        },
        {
            "val": 13.878,
            "s": 30,
            "d": 16
        },
        {
            "val": 17.712,
            "s": 1,
            "d": 17
        },
        {
            "val": 7.432,
            "s": 2,
            "d": 17
        },
        {
            "val": 19.23,
            "s": 3,
            "d": 17
        },
        {
            "val": 10.3,
            "s": 4,
            "d": 17
        },
        {
            "val": 9.286,
            "s": 5,
            "d": 17
        },
        {
            "val": 8.957,
            "s": 6,
            "d": 17
        },
        {
            "val": 11.183,
            "s": 7,
            "d": 17
        },
        {
            "val": 9.952,
            "s": 8,
            "d": 17
        },
        {
            "val": 13.902,
            "s": 9,
            "d": 17
        },
        {
            "val": 19.633,
            "s": 10,
            "d": 17
        },
        {
            "val": 7.469,
            "s": 11,
            "d": 17
        },
        {
            "val": 14.238,
            "s": 12,
            "d": 17
        },
        {
            "val": 18.635,
            "s": 13,
            "d": 17
        },
        {
            "val": 5.291,
            "s": 14,
            "d": 17
        },
        {
            "val": 15.771,
            "s": 15,
            "d": 17
        },
        {
            "val": 11.645,
            "s": 16,
            "d": 17
        },
        {
            "val": 15.219,
            "s": 17,
            "d": 17
        },
        {
            "val": 9.569,
            "s": 18,
            "d": 17
        },
        {
            "val": 6.932,
            "s": 19,
            "d": 17
        },
        {
            "val": 5.605,
            "s": 20,
            "d": 17
        },
        {
            "val": 10.814,
            "s": 21,
            "d": 17
        },
        {
            "val": 17.925,
            "s": 22,
            "d": 17
        },
        {
            "val": 14.211,
            "s": 23,
            "d": 17
        },
        {
            "val": 16.467,
            "s": 24,
            "d": 17
        },
        {
            "val": 18.572,
            "s": 25,
            "d": 17
        },
        {
            "val": 14.381,
            "s": 26,
            "d": 17
        },
        {
            "val": 10.168,
            "s": 27,
            "d": 17
        },
        {
            "val": 5.913,
            "s": 28,
            "d": 17
        },
        {
            "val": 7.908,
            "s": 29,
            "d": 17
        },
        {
            "val": 11.996,
            "s": 30,
            "d": 17
        },
        {
            "val": 9.923,
            "s": 1,
            "d": 18
        },
        {
            "val": 18.344,
            "s": 2,
            "d": 18
        },
        {
            "val": 18.273,
            "s": 3,
            "d": 18
        },
        {
            "val": 13.384,
            "s": 4,
            "d": 18
        },
        {
            "val": 5.47,
            "s": 5,
            "d": 18
        },
        {
            "val": 7.654,
            "s": 6,
            "d": 18
        },
        {
            "val": 13.017,
            "s": 7,
            "d": 18
        },
        {
            "val": 9.037,
            "s": 8,
            "d": 18
        },
        {
            "val": 11.067,
            "s": 9,
            "d": 18
        },
        {
            "val": 8.286,
            "s": 10,
            "d": 18
        },
        {
            "val": 8.675,
            "s": 11,
            "d": 18
        },
        {
            "val": 18.779,
            "s": 12,
            "d": 18
        },
        {
            "val": 7.44,
            "s": 13,
            "d": 18
        },
        {
            "val": 16.467,
            "s": 14,
            "d": 18
        },
        {
            "val": 18.122,
            "s": 15,
            "d": 18
        },
        {
            "val": 18.035,
            "s": 16,
            "d": 18
        },
        {
            "val": 10.078,
            "s": 17,
            "d": 18
        },
        {
            "val": 9.889,
            "s": 18,
            "d": 18
        },
        {
            "val": 18.758,
            "s": 19,
            "d": 18
        },
        {
            "val": 15.892,
            "s": 20,
            "d": 18
        },
        {
            "val": 7.309,
            "s": 21,
            "d": 18
        },
        {
            "val": 7.671,
            "s": 22,
            "d": 18
        },
        {
            "val": 19.934,
            "s": 23,
            "d": 18
        },
        {
            "val": 16.03,
            "s": 24,
            "d": 18
        },
        {
            "val": 6.432,
            "s": 25,
            "d": 18
        },
        {
            "val": 12.257,
            "s": 26,
            "d": 18
        },
        {
            "val": 11.774,
            "s": 27,
            "d": 18
        },
        {
            "val": 18.335,
            "s": 28,
            "d": 18
        },
        {
            "val": 11.872,
            "s": 29,
            "d": 18
        },
        {
            "val": 17.503,
            "s": 30,
            "d": 18
        },
        {
            "val": 19.244,
            "s": 1,
            "d": 19
        },
        {
            "val": 7.019,
            "s": 2,
            "d": 19
        },
        {
            "val": 15.541,
            "s": 3,
            "d": 19
        },
        {
            "val": 8.612,
            "s": 4,
            "d": 19
        },
        {
            "val": 19.951,
            "s": 5,
            "d": 19
        },
        {
            "val": 17.446,
            "s": 6,
            "d": 19
        },
        {
            "val": 10.454,
            "s": 7,
            "d": 19
        },
        {
            "val": 7.896,
            "s": 8,
            "d": 19
        },
        {
            "val": 18.428,
            "s": 9,
            "d": 19
        },
        {
            "val": 10.598,
            "s": 10,
            "d": 19
        },
        {
            "val": 13.976,
            "s": 11,
            "d": 19
        },
        {
            "val": 13.807,
            "s": 12,
            "d": 19
        },
        {
            "val": 16.158,
            "s": 13,
            "d": 19
        },
        {
            "val": 11.377,
            "s": 14,
            "d": 19
        },
        {
            "val": 8.946,
            "s": 15,
            "d": 19
        },
        {
            "val": 19.144,
            "s": 16,
            "d": 19
        },
        {
            "val": 10.572,
            "s": 17,
            "d": 19
        },
        {
            "val": 11.071,
            "s": 18,
            "d": 19
        },
        {
            "val": 16.834,
            "s": 19,
            "d": 19
        },
        {
            "val": 17.902,
            "s": 20,
            "d": 19
        },
        {
            "val": 5.507,
            "s": 21,
            "d": 19
        },
        {
            "val": 5.621,
            "s": 22,
            "d": 19
        },
        {
            "val": 18.929,
            "s": 23,
            "d": 19
        },
        {
            "val": 15.59,
            "s": 24,
            "d": 19
        },
        {
            "val": 12.261,
            "s": 25,
            "d": 19
        },
        {
            "val": 6.586,
            "s": 26,
            "d": 19
        },
        {
            "val": 16.014,
            "s": 27,
            "d": 19
        },
        {
            "val": 8.832,
            "s": 28,
            "d": 19
        },
        {
            "val": 16.066,
            "s": 29,
            "d": 19
        },
        {
            "val": 16.916,
            "s": 30,
            "d": 19
        },
        {
            "val": 8.545,
            "s": 1,
            "d": 20
        },
        {
            "val": 9.671,
            "s": 2,
            "d": 20
        },
        {
            "val": 10.313,
            "s": 3,
            "d": 20
        },
        {
            "val": 15.957,
            "s": 4,
            "d": 20
        },
        {
            "val": 6.144,
            "s": 5,
            "d": 20
        },
        {
            "val": 16.196,
            "s": 6,
            "d": 20
        },
        {
            "val": 19.495,
            "s": 7,
            "d": 20
        },
        {
            "val": 11.638,
            "s": 8,
            "d": 20
        },
        {
            "val": 14.762,
            "s": 9,
            "d": 20
        },
        {
            "val": 9.878,
            "s": 10,
            "d": 20
        },
        {
            "val": 10.246,
            "s": 11,
            "d": 20
        },
        {
            "val": 7.716,
            "s": 12,
            "d": 20
        },
        {
            "val": 15.532,
            "s": 13,
            "d": 20
        },
        {
            "val": 6.706,
            "s": 14,
            "d": 20
        },
        {
            "val": 9.218,
            "s": 15,
            "d": 20
        },
        {
            "val": 18.794,
            "s": 16,
            "d": 20
        },
        {
            "val": 8.258,
            "s": 17,
            "d": 20
        },
        {
            "val": 13.449,
            "s": 18,
            "d": 20
        },
        {
            "val": 5.981,
            "s": 19,
            "d": 20
        },
        {
            "val": 16.282,
            "s": 20,
            "d": 20
        },
        {
            "val": 7.486,
            "s": 21,
            "d": 20
        },
        {
            "val": 7.327,
            "s": 22,
            "d": 20
        },
        {
            "val": 7.166,
            "s": 23,
            "d": 20
        },
        {
            "val": 7.401,
            "s": 24,
            "d": 20
        },
        {
            "val": 7.503,
            "s": 25,
            "d": 20
        },
        {
            "val": 19.646,
            "s": 26,
            "d": 20
        },
        {
            "val": 6.671,
            "s": 27,
            "d": 20
        },
        {
            "val": 16.136,
            "s": 28,
            "d": 20
        },
        {
            "val": 6.827,
            "s": 29,
            "d": 20
        },
        {
            "val": 19.884,
            "s": 30,
            "d": 20
        },
        {
            "val": 8.126,
            "s": 1,
            "d": 21
        },
        {
            "val": 8.294,
            "s": 2,
            "d": 21
        },
        {
            "val": 17.579,
            "s": 3,
            "d": 21
        },
        {
            "val": 15.756,
            "s": 4,
            "d": 21
        },
        {
            "val": 7.551,
            "s": 5,
            "d": 21
        },
        {
            "val": 18.113,
            "s": 6,
            "d": 21
        },
        {
            "val": 8.489,
            "s": 7,
            "d": 21
        },
        {
            "val": 13.185,
            "s": 8,
            "d": 21
        },
        {
            "val": 8.044,
            "s": 9,
            "d": 21
        },
        {
            "val": 13.309,
            "s": 10,
            "d": 21
        },
        {
            "val": 15.42,
            "s": 11,
            "d": 21
        },
        {
            "val": 15.558,
            "s": 12,
            "d": 21
        },
        {
            "val": 16.347,
            "s": 13,
            "d": 21
        },
        {
            "val": 11.747,
            "s": 14,
            "d": 21
        },
        {
            "val": 18.488,
            "s": 15,
            "d": 21
        },
        {
            "val": 18.807,
            "s": 16,
            "d": 21
        },
        {
            "val": 15.951,
            "s": 17,
            "d": 21
        },
        {
            "val": 8.139,
            "s": 18,
            "d": 21
        },
        {
            "val": 15.576,
            "s": 19,
            "d": 21
        },
        {
            "val": 19.487,
            "s": 20,
            "d": 21
        },
        {
            "val": 16.119,
            "s": 21,
            "d": 21
        },
        {
            "val": 19.413,
            "s": 22,
            "d": 21
        },
        {
            "val": 7.107,
            "s": 23,
            "d": 21
        },
        {
            "val": 6.169,
            "s": 24,
            "d": 21
        },
        {
            "val": 18.438,
            "s": 25,
            "d": 21
        },
        {
            "val": 10.445,
            "s": 26,
            "d": 21
        },
        {
            "val": 7.975,
            "s": 27,
            "d": 21
        },
        {
            "val": 8.156,
            "s": 28,
            "d": 21
        },
        {
            "val": 9.611,
            "s": 29,
            "d": 21
        },
        {
            "val": 6.453,
            "s": 30,
            "d": 21
        },
        {
            "val": 15.874,
            "s": 1,
            "d": 22
        },
        {
            "val": 12.654,
            "s": 2,
            "d": 22
        },
        {
            "val": 12.017,
            "s": 3,
            "d": 22
        },
        {
            "val": 12.386,
            "s": 4,
            "d": 22
        },
        {
            "val": 18.679,
            "s": 5,
            "d": 22
        },
        {
            "val": 15.732,
            "s": 6,
            "d": 22
        },
        {
            "val": 14.346,
            "s": 7,
            "d": 22
        },
        {
            "val": 16.901,
            "s": 8,
            "d": 22
        },
        {
            "val": 18.937,
            "s": 9,
            "d": 22
        },
        {
            "val": 10.31,
            "s": 10,
            "d": 22
        },
        {
            "val": 11.496,
            "s": 11,
            "d": 22
        },
        {
            "val": 6.249,
            "s": 12,
            "d": 22
        },
        {
            "val": 19.788,
            "s": 13,
            "d": 22
        },
        {
            "val": 12.656,
            "s": 14,
            "d": 22
        },
        {
            "val": 15.094,
            "s": 15,
            "d": 22
        },
        {
            "val": 9.201,
            "s": 16,
            "d": 22
        },
        {
            "val": 11.679,
            "s": 17,
            "d": 22
        },
        {
            "val": 19.378,
            "s": 18,
            "d": 22
        },
        {
            "val": 18.496,
            "s": 19,
            "d": 22
        },
        {
            "val": 10.839,
            "s": 20,
            "d": 22
        },
        {
            "val": 5.092,
            "s": 21,
            "d": 22
        },
        {
            "val": 17.153,
            "s": 22,
            "d": 22
        },
        {
            "val": 5.638,
            "s": 23,
            "d": 22
        },
        {
            "val": 10.27,
            "s": 24,
            "d": 22
        },
        {
            "val": 7.424,
            "s": 25,
            "d": 22
        },
        {
            "val": 7.808,
            "s": 26,
            "d": 22
        },
        {
            "val": 19.324,
            "s": 27,
            "d": 22
        },
        {
            "val": 18.326,
            "s": 28,
            "d": 22
        },
        {
            "val": 17.265,
            "s": 29,
            "d": 22
        },
        {
            "val": 11.376,
            "s": 30,
            "d": 22
        },
        {
            "val": 12.946,
            "s": 1,
            "d": 23
        },
        {
            "val": 6.005,
            "s": 2,
            "d": 23
        },
        {
            "val": 15.218,
            "s": 3,
            "d": 23
        },
        {
            "val": 17.267,
            "s": 4,
            "d": 23
        },
        {
            "val": 8.509,
            "s": 5,
            "d": 23
        },
        {
            "val": 12.02,
            "s": 6,
            "d": 23
        },
        {
            "val": 14.83,
            "s": 7,
            "d": 23
        },
        {
            "val": 16.135,
            "s": 8,
            "d": 23
        },
        {
            "val": 15.935,
            "s": 9,
            "d": 23
        },
        {
            "val": 10.879,
            "s": 10,
            "d": 23
        },
        {
            "val": 17.135,
            "s": 11,
            "d": 23
        },
        {
            "val": 13.785,
            "s": 12,
            "d": 23
        },
        {
            "val": 19.72,
            "s": 13,
            "d": 23
        },
        {
            "val": 5.252,
            "s": 14,
            "d": 23
        },
        {
            "val": 10.316,
            "s": 15,
            "d": 23
        },
        {
            "val": 12.796,
            "s": 16,
            "d": 23
        },
        {
            "val": 17.477,
            "s": 17,
            "d": 23
        },
        {
            "val": 13.127,
            "s": 18,
            "d": 23
        },
        {
            "val": 8.22,
            "s": 19,
            "d": 23
        },
        {
            "val": 14.767,
            "s": 20,
            "d": 23
        },
        {
            "val": 12.596,
            "s": 21,
            "d": 23
        },
        {
            "val": 12.897,
            "s": 22,
            "d": 23
        },
        {
            "val": 16.343,
            "s": 23,
            "d": 23
        },
        {
            "val": 7.546,
            "s": 24,
            "d": 23
        },
        {
            "val": 12.108,
            "s": 25,
            "d": 23
        },
        {
            "val": 16.569,
            "s": 26,
            "d": 23
        },
        {
            "val": 12.644,
            "s": 27,
            "d": 23
        },
        {
            "val": 17.737,
            "s": 28,
            "d": 23
        },
        {
            "val": 6.111,
            "s": 29,
            "d": 23
        },
        {
            "val": 19.307,
            "s": 30,
            "d": 23
        },
        {
            "val": 12.96,
            "s": 1,
            "d": 24
        },
        {
            "val": 13.468,
            "s": 2,
            "d": 24
        },
        {
            "val": 7.889,
            "s": 3,
            "d": 24
        },
        {
            "val": 15.111,
            "s": 4,
            "d": 24
        },
        {
            "val": 16.457,
            "s": 5,
            "d": 24
        },
        {
            "val": 12.305,
            "s": 6,
            "d": 24
        },
        {
            "val": 7.826,
            "s": 7,
            "d": 24
        },
        {
            "val": 14.446,
            "s": 8,
            "d": 24
        },
        {
            "val": 10.566,
            "s": 9,
            "d": 24
        },
        {
            "val": 10.282,
            "s": 10,
            "d": 24
        },
        {
            "val": 9.933,
            "s": 11,
            "d": 24
        },
        {
            "val": 14.324,
            "s": 12,
            "d": 24
        },
        {
            "val": 19.044,
            "s": 13,
            "d": 24
        },
        {
            "val": 9.422,
            "s": 14,
            "d": 24
        },
        {
            "val": 9.96,
            "s": 15,
            "d": 24
        },
        {
            "val": 19.451,
            "s": 16,
            "d": 24
        },
        {
            "val": 7.075,
            "s": 17,
            "d": 24
        },
        {
            "val": 10.984,
            "s": 18,
            "d": 24
        },
        {
            "val": 8.58,
            "s": 19,
            "d": 24
        },
        {
            "val": 13.89,
            "s": 20,
            "d": 24
        },
        {
            "val": 15.066,
            "s": 21,
            "d": 24
        },
        {
            "val": 6.036,
            "s": 22,
            "d": 24
        },
        {
            "val": 19.983,
            "s": 23,
            "d": 24
        },
        {
            "val": 14.072,
            "s": 24,
            "d": 24
        },
        {
            "val": 10.233,
            "s": 25,
            "d": 24
        },
        {
            "val": 18.897,
            "s": 26,
            "d": 24
        },
        {
            "val": 6.128,
            "s": 27,
            "d": 24
        },
        {
            "val": 10.849,
            "s": 28,
            "d": 24
        },
        {
            "val": 9.004,
            "s": 29,
            "d": 24
        },
        {
            "val": 8.444,
            "s": 30,
            "d": 24
        },
        {
            "val": 7.186,
            "s": 1,
            "d": 25
        },
        {
            "val": 12.208,
            "s": 2,
            "d": 25
        },
        {
            "val": 12.709,
            "s": 3,
            "d": 25
        },
        {
            "val": 11.134,
            "s": 4,
            "d": 25
        },
        {
            "val": 10.815,
            "s": 5,
            "d": 25
        },
        {
            "val": 15.488,
            "s": 6,
            "d": 25
        },
        {
            "val": 8.31,
            "s": 7,
            "d": 25
        },
        {
            "val": 12.89,
            "s": 8,
            "d": 25
        },
        {
            "val": 11.728,
            "s": 9,
            "d": 25
        },
        {
            "val": 17.824,
            "s": 10,
            "d": 25
        },
        {
            "val": 5.63,
            "s": 11,
            "d": 25
        },
        {
            "val": 9.218,
            "s": 12,
            "d": 25
        },
        {
            "val": 18.787,
            "s": 13,
            "d": 25
        },
        {
            "val": 17.229,
            "s": 14,
            "d": 25
        },
        {
            "val": 15.389,
            "s": 15,
            "d": 25
        },
        {
            "val": 12.293,
            "s": 16,
            "d": 25
        },
        {
            "val": 16.169,
            "s": 17,
            "d": 25
        },
        {
            "val": 19.181,
            "s": 18,
            "d": 25
        },
        {
            "val": 9.59,
            "s": 19,
            "d": 25
        },
        {
            "val": 14.961,
            "s": 20,
            "d": 25
        },
        {
            "val": 13.875,
            "s": 21,
            "d": 25
        },
        {
            "val": 13.655,
            "s": 22,
            "d": 25
        },
        {
            "val": 8.248,
            "s": 23,
            "d": 25
        },
        {
            "val": 18.928,
            "s": 24,
            "d": 25
        },
        {
            "val": 13.663,
            "s": 25,
            "d": 25
        },
        {
            "val": 5.31,
            "s": 26,
            "d": 25
        },
        {
            "val": 10.443,
            "s": 27,
            "d": 25
        },
        {
            "val": 8.967,
            "s": 28,
            "d": 25
        },
        {
            "val": 11.927,
            "s": 29,
            "d": 25
        },
        {
            "val": 13.5,
            "s": 30,
            "d": 25
        },
        {
            "val": 6.471,
            "s": 1,
            "d": 26
        },
        {
            "val": 9.696,
            "s": 2,
            "d": 26
        },
        {
            "val": 6.632,
            "s": 3,
            "d": 26
        },
        {
            "val": 5.427,
            "s": 4,
            "d": 26
        },
        {
            "val": 15.436,
            "s": 5,
            "d": 26
        },
        {
            "val": 13.182,
            "s": 6,
            "d": 26
        },
        {
            "val": 16.363,
            "s": 7,
            "d": 26
        },
        {
            "val": 16.762,
            "s": 8,
            "d": 26
        },
        {
            "val": 7.684,
            "s": 9,
            "d": 26
        },
        {
            "val": 16.66,
            "s": 10,
            "d": 26
        },
        {
            "val": 19.191,
            "s": 11,
            "d": 26
        },
        {
            "val": 13.956,
            "s": 12,
            "d": 26
        },
        {
            "val": 16.927,
            "s": 13,
            "d": 26
        },
        {
            "val": 7.255,
            "s": 14,
            "d": 26
        },
        {
            "val": 11.703,
            "s": 15,
            "d": 26
        },
        {
            "val": 10.403,
            "s": 16,
            "d": 26
        },
        {
            "val": 9.022,
            "s": 17,
            "d": 26
        },
        {
            "val": 18.027,
            "s": 18,
            "d": 26
        },
        {
            "val": 9.427,
            "s": 19,
            "d": 26
        },
        {
            "val": 12.363,
            "s": 20,
            "d": 26
        },
        {
            "val": 16.773,
            "s": 21,
            "d": 26
        },
        {
            "val": 5.558,
            "s": 22,
            "d": 26
        },
        {
            "val": 9.172,
            "s": 23,
            "d": 26
        },
        {
            "val": 12.291,
            "s": 24,
            "d": 26
        },
        {
            "val": 7.099,
            "s": 25,
            "d": 26
        },
        {
            "val": 18.024,
            "s": 26,
            "d": 26
        },
        {
            "val": 16.544,
            "s": 27,
            "d": 26
        },
        {
            "val": 5.383,
            "s": 28,
            "d": 26
        },
        {
            "val": 16.141,
            "s": 29,
            "d": 26
        },
        {
            "val": 13.209,
            "s": 30,
            "d": 26
        },
        {
            "val": 11.383,
            "s": 1,
            "d": 27
        },
        {
            "val": 18.7,
            "s": 2,
            "d": 27
        },
        {
            "val": 8.037,
            "s": 3,
            "d": 27
        },
        {
            "val": 16.967,
            "s": 4,
            "d": 27
        },
        {
            "val": 16.064,
            "s": 5,
            "d": 27
        },
        {
            "val": 13.25,
            "s": 6,
            "d": 27
        },
        {
            "val": 18.335,
            "s": 7,
            "d": 27
        },
        {
            "val": 7.922,
            "s": 8,
            "d": 27
        },
        {
            "val": 10.595,
            "s": 9,
            "d": 27
        },
        {
            "val": 12.39,
            "s": 10,
            "d": 27
        },
        {
            "val": 8.462,
            "s": 11,
            "d": 27
        },
        {
            "val": 18.691,
            "s": 12,
            "d": 27
        },
        {
            "val": 9.571,
            "s": 13,
            "d": 27
        },
        {
            "val": 12.032,
            "s": 14,
            "d": 27
        },
        {
            "val": 9.589,
            "s": 15,
            "d": 27
        },
        {
            "val": 19.215,
            "s": 16,
            "d": 27
        },
        {
            "val": 14.844,
            "s": 17,
            "d": 27
        },
        {
            "val": 9.533,
            "s": 18,
            "d": 27
        },
        {
            "val": 6.375,
            "s": 19,
            "d": 27
        },
        {
            "val": 7.796,
            "s": 20,
            "d": 27
        },
        {
            "val": 9.741,
            "s": 21,
            "d": 27
        },
        {
            "val": 5.043,
            "s": 22,
            "d": 27
        },
        {
            "val": 6.337,
            "s": 23,
            "d": 27
        },
        {
            "val": 8.158,
            "s": 24,
            "d": 27
        },
        {
            "val": 10.64,
            "s": 25,
            "d": 27
        },
        {
            "val": 18.492,
            "s": 26,
            "d": 27
        },
        {
            "val": 8.065,
            "s": 27,
            "d": 27
        },
        {
            "val": 5.466,
            "s": 28,
            "d": 27
        },
        {
            "val": 17.972,
            "s": 29,
            "d": 27
        },
        {
            "val": 8.026,
            "s": 30,
            "d": 27
        },
        {
            "val": 13.466,
            "s": 1,
            "d": 28
        },
        {
            "val": 9.708,
            "s": 2,
            "d": 28
        },
        {
            "val": 9.686,
            "s": 3,
            "d": 28
        },
        {
            "val": 15.227,
            "s": 4,
            "d": 28
        },
        {
            "val": 10.067,
            "s": 5,
            "d": 28
        },
        {
            "val": 11.846,
            "s": 6,
            "d": 28
        },
        {
            "val": 11.052,
            "s": 7,
            "d": 28
        },
        {
            "val": 11.848,
            "s": 8,
            "d": 28
        },
        {
            "val": 5.656,
            "s": 9,
            "d": 28
        },
        {
            "val": 18.93,
            "s": 10,
            "d": 28
        },
        {
            "val": 8.502,
            "s": 11,
            "d": 28
        },
        {
            "val": 18.631,
            "s": 12,
            "d": 28
        },
        {
            "val": 18.873,
            "s": 13,
            "d": 28
        },
        {
            "val": 11.284,
            "s": 14,
            "d": 28
        },
        {
            "val": 14.984,
            "s": 15,
            "d": 28
        },
        {
            "val": 15.61,
            "s": 16,
            "d": 28
        },
        {
            "val": 13.064,
            "s": 17,
            "d": 28
        },
        {
            "val": 5.53,
            "s": 18,
            "d": 28
        },
        {
            "val": 5.654,
            "s": 19,
            "d": 28
        },
        {
            "val": 7.044,
            "s": 20,
            "d": 28
        },
        {
            "val": 9.941,
            "s": 21,
            "d": 28
        },
        {
            "val": 9.172,
            "s": 22,
            "d": 28
        },
        {
            "val": 19.652,
            "s": 23,
            "d": 28
        },
        {
            "val": 7.409,
            "s": 24,
            "d": 28
        },
        {
            "val": 17.295,
            "s": 25,
            "d": 28
        },
        {
            "val": 10.65,
            "s": 26,
            "d": 28
        },
        {
            "val": 7.489,
            "s": 27,
            "d": 28
        },
        {
            "val": 12.922,
            "s": 28,
            "d": 28
        },
        {
            "val": 14.722,
            "s": 29,
            "d": 28
        },
        {
            "val": 18.021,
            "s": 30,
            "d": 28
        },
        {
            "val": 10.724,
            "s": 1,
            "d": 29
        },
        {
            "val": 17.412,
            "s": 2,
            "d": 29
        },
        {
            "val": 15.946,
            "s": 3,
            "d": 29
        },
        {
            "val": 8.171,
            "s": 4,
            "d": 29
        },
        {
            "val": 11.742,
            "s": 5,
            "d": 29
        },
        {
            "val": 13.348,
            "s": 6,
            "d": 29
        },
        {
            "val": 10.476,
            "s": 7,
            "d": 29
        },
        {
            "val": 14.066,
            "s": 8,
            "d": 29
        },
        {
            "val": 15.123,
            "s": 9,
            "d": 29
        },
        {
            "val": 5.628,
            "s": 10,
            "d": 29
        },
        {
            "val": 8.784,
            "s": 11,
            "d": 29
        },
        {
            "val": 16.84,
            "s": 12,
            "d": 29
        },
        {
            "val": 17.865,
            "s": 13,
            "d": 29
        },
        {
            "val": 14.544,
            "s": 14,
            "d": 29
        },
        {
            "val": 12.681,
            "s": 15,
            "d": 29
        },
        {
            "val": 19.736,
            "s": 16,
            "d": 29
        },
        {
            "val": 17.43,
            "s": 17,
            "d": 29
        },
        {
            "val": 17.966,
            "s": 18,
            "d": 29
        },
        {
            "val": 17.173,
            "s": 19,
            "d": 29
        },
        {
            "val": 15.327,
            "s": 20,
            "d": 29
        },
        {
            "val": 13.1,
            "s": 21,
            "d": 29
        },
        {
            "val": 6.49,
            "s": 22,
            "d": 29
        },
        {
            "val": 6.382,
            "s": 23,
            "d": 29
        },
        {
            "val": 16.62,
            "s": 24,
            "d": 29
        },
        {
            "val": 9.55,
            "s": 25,
            "d": 29
        },
        {
            "val": 16.394,
            "s": 26,
            "d": 29
        },
        {
            "val": 15.068,
            "s": 27,
            "d": 29
        },
        {
            "val": 9.026,
            "s": 28,
            "d": 29
        },
        {
            "val": 11.82,
            "s": 29,
            "d": 29
        },
        {
            "val": 6.887,
            "s": 30,
            "d": 29
        },
        {
            "val": 6.702,
            "s": 1,
            "d": 30
        },
        {
            "val": 9.388,
            "s": 2,
            "d": 30
        },
        {
            "val": 9.372,
            "s": 3,
            "d": 30
        },
        {
            "val": 17.616,
            "s": 4,
            "d": 30
        },
        {
            "val": 14.13,
            "s": 5,
            "d": 30
        },
        {
            "val": 10.108,
            "s": 6,
            "d": 30
        },
        {
            "val": 17.303,
            "s": 7,
            "d": 30
        },
        {
            "val": 6.896,
            "s": 8,
            "d": 30
        },
        {
            "val": 16.976,
            "s": 9,
            "d": 30
        },
        {
            "val": 10.485,
            "s": 10,
            "d": 30
        },
        {
            "val": 17.59,
            "s": 11,
            "d": 30
        },
        {
            "val": 7.088,
            "s": 12,
            "d": 30
        },
        {
            "val": 14.999,
            "s": 13,
            "d": 30
        },
        {
            "val": 17.223,
            "s": 14,
            "d": 30
        },
        {
            "val": 19.624,
            "s": 15,
            "d": 30
        },
        {
            "val": 6.121,
            "s": 16,
            "d": 30
        },
        {
            "val": 10.714,
            "s": 17,
            "d": 30
        },
        {
            "val": 8.41,
            "s": 18,
            "d": 30
        },
        {
            "val": 5.002,
            "s": 19,
            "d": 30
        },
        {
            "val": 7.635,
            "s": 20,
            "d": 30
        },
        {
            "val": 7.116,
            "s": 21,
            "d": 30
        },
        {
            "val": 17.696,
            "s": 22,
            "d": 30
        },
        {
            "val": 19.332,
            "s": 23,
            "d": 30
        },
        {
            "val": 14.232,
            "s": 24,
            "d": 30
        },
        {
            "val": 11.706,
            "s": 25,
            "d": 30
        },
        {
            "val": 18.024,
            "s": 26,
            "d": 30
        },
        {
            "val": 10.0,
            "s": 27,
            "d": 30
        },
        {
            "val": 9.133,
            "s": 28,
            "d": 30
        },
        {
            "val": 7.872,
            "s": 29,
            "d": 30
        },
        {
            "val": 17.441,
            "s": 30,
            "d": 30
        }
    ]
}
